{
  "name": "Bashi Channel",
  "type": "strait",
  "region": "Western Pacific",
  "bounds": {
    "north": 22.0,
    "south": 20.0,
    "east": 122.5,
    "west": 120.5
  },
  "center": {
    "lat": 21.0,
    "lon": 121.5
  },
  "min_depth_m": 1000,
  "min_width_km": 150,
  "strategic_value": "high",
  "carrier_navigable": true,
  "notes": "Southern component of the Luzon Strait, important for naval access between the Philippine Sea and South China Sea.",
  "wikipedia_url": "https://en.wikipedia.org/wiki/Bashi_Channel"
}
