{
  "name": "Taiwan Strait",
  "type": "strait",
  "region": "East Asia",
  "bounds": [
    {
      "lat": 26.3,
      "lon": 117
    },
    {
      "lat": 26.3,
      "lon": 121.5
    },
    {
      "lat": 22,
      "lon": 121.5
    },
    {
      "lat": 22,
      "lon": 117
    }
  ],
  "center": {
    "lat": 24.2,
    "lon": 119.3
  },
  "min_depth_m": 60,
  "min_width_km": 130,
  "strategic_value": "critical",
  "carrier_navigable": true,
  "notes": "Strategic passage between Taiwan and mainland China.",
  "wikipedia_url": "https://en.wikipedia.org/wiki/Taiwan_Strait"
}
